How2jJavaZhongjiJiaochengFix1/README.md
How2jJavaZhongjiJiaochengFix1/__init__.py
How2jJavaZhongjiJiaochengFix1/__main__.py
How2jJavaZhongjiJiaochengFix1/file.epub
How2jJavaZhongjiJiaochengFix1/index.html
How2jJavaZhongjiJiaochengFix1/css/__init__.py
How2jJavaZhongjiJiaochengFix1/css/annotations.css
How2jJavaZhongjiJiaochengFix1/css/main.css
How2jJavaZhongjiJiaochengFix1/css/normalize.css
How2jJavaZhongjiJiaochengFix1/css/popup.css
How2jJavaZhongjiJiaochengFix1/font/__init__.py
How2jJavaZhongjiJiaochengFix1/font/fontello.eot
How2jJavaZhongjiJiaochengFix1/font/fontello.svg
How2jJavaZhongjiJiaochengFix1/font/fontello.ttf
How2jJavaZhongjiJiaochengFix1/font/fontello.woff
How2jJavaZhongjiJiaochengFix1/img/__init__.py
How2jJavaZhongjiJiaochengFix1/img/annotator-glyph-sprite.png
How2jJavaZhongjiJiaochengFix1/img/annotator-icon-sprite.png
How2jJavaZhongjiJiaochengFix1/img/apple-touch-icon.png
How2jJavaZhongjiJiaochengFix1/img/cancelfullscreen.png
How2jJavaZhongjiJiaochengFix1/img/close.png
How2jJavaZhongjiJiaochengFix1/img/fullscreen.png
How2jJavaZhongjiJiaochengFix1/img/loader.gif
How2jJavaZhongjiJiaochengFix1/img/menu-icon.png
How2jJavaZhongjiJiaochengFix1/img/save.png
How2jJavaZhongjiJiaochengFix1/img/saved.png
How2jJavaZhongjiJiaochengFix1/img/settings-s.png
How2jJavaZhongjiJiaochengFix1/img/settings.png
How2jJavaZhongjiJiaochengFix1/img/star.png
How2jJavaZhongjiJiaochengFix1/js/__init__.py
How2jJavaZhongjiJiaochengFix1/js/epub.js
How2jJavaZhongjiJiaochengFix1/js/epub.min.js
How2jJavaZhongjiJiaochengFix1/js/epub.min.map
How2jJavaZhongjiJiaochengFix1/js/hooks.min.js
How2jJavaZhongjiJiaochengFix1/js/hooks.min.map
How2jJavaZhongjiJiaochengFix1/js/reader.js
How2jJavaZhongjiJiaochengFix1/js/reader.js.map
How2jJavaZhongjiJiaochengFix1/js/reader.min.js
How2jJavaZhongjiJiaochengFix1/js/reader.min.map
How2jJavaZhongjiJiaochengFix1/js/hooks/__init__.py
How2jJavaZhongjiJiaochengFix1/js/hooks/extensions/__init__.py
How2jJavaZhongjiJiaochengFix1/js/hooks/extensions/highlight.js
how2j_java_zhongji_jiaocheng_fix1-2025.3.25.0.dist-info/METADATA
how2j_java_zhongji_jiaocheng_fix1-2025.3.25.0.dist-info/WHEEL
how2j_java_zhongji_jiaocheng_fix1-2025.3.25.0.dist-info/entry_points.txt
how2j_java_zhongji_jiaocheng_fix1-2025.3.25.0.dist-info/top_level.txt
how2j_java_zhongji_jiaocheng_fix1-2025.3.25.0.dist-info/RECORD
